<?xml version="1.0" encoding="UTF-8"?>
<vxml version="2.1">

<!--
   English main menu.
-->
<menu id="main" dtmf="true">
    <prompt>Welcome to Afri Cereal. Your application to exchange, sell, or buy seeds. 
    You can write or receive messages, join groups, or receive seed specific information. 
    What would you like to do? <enumerate/>
    </prompt>
    <choice next="BSE/exchanging_seeds.xml"> Exchange seeds </choice>
    <choice next="BSE/selling_seeds.xml"> Sell seeds </choice>
    <choice next="BSE/buying_seeds.xml"> Buy seeds </choice>
    <choice next="Inventory/inventory_menu.xml">Seed information</choice>
    <choice next="../welcome.xml">Go back to go back to the main menu.</choice>

    <noinput>Sorry, I didn't catch that.<reprompt/></noinput>
    <nomatch>Sorry, that does not match any of the options.<reprompt/></nomatch>
</menu>
</vxml>